hacs_persistence/__init__.py
hacs_persistence/adapter.py
hacs_persistence/connection_factory.py
hacs_persistence/granular_adapter.py
hacs_persistence/migrations.py
hacs_persistence/repositories.py
hacs_persistence/resource_mapper.py
hacs_persistence/schema.py
hacs_persistence/vector_store.py
hacs_persistence-0.4.3.dist-info/METADATA
hacs_persistence-0.4.3.dist-info/WHEEL
hacs_persistence-0.4.3.dist-info/RECORD
