Metadata-Version: 2.4
Name: hacs-persistence
Version: 0.4.3
Summary: Database and vector store persistence adapters for HACS
Project-URL: Homepage, https://github.com/solanovisitor/hacs-ai
Project-URL: Documentation, https://github.com/solanovisitor/hacs-ai/blob/main/docs/
Project-URL: Repository, https://github.com/solanovisitor/hacs-ai
Project-URL: Issues, https://github.com/solanovisitor/hacs-ai/issues
Project-URL: Changelog, https://github.com/solanovisitor/hacs-ai/blob/main/CHANGELOG.md
Author-email: Solano Todeschini <solanovisitor@gmail.com>
Maintainer-email: Solano Todeschini <solanovisitor@gmail.com>
License: MIT
Keywords: ai,database,fhir,healthcare,persistence,vector-store
Classifier: Development Status :: 4 - Beta
Classifier: Intended Audience :: Developers
Classifier: Intended Audience :: Healthcare Industry
Classifier: License :: OSI Approved :: MIT License
Classifier: Programming Language :: Python :: 3
Classifier: Programming Language :: Python :: 3.11
Classifier: Programming Language :: Python :: 3.12
Classifier: Topic :: Scientific/Engineering :: Medical Science Apps.
Classifier: Topic :: Software Development :: Libraries :: Python Modules
Requires-Python: >=3.11
Requires-Dist: hacs-core>=0.4.3
Requires-Dist: pydantic>=2.11.7
Requires-Dist: sqlalchemy>=2.0.0
Provides-Extra: all
Requires-Dist: pgvector>=0.2.4; extra == 'all'
Requires-Dist: pinecone>=7.3.0; extra == 'all'
Requires-Dist: psycopg[async,binary]>=3.2.9; extra == 'all'
Requires-Dist: qdrant-client>=1.15.1; extra == 'all'
Provides-Extra: dev
Requires-Dist: pytest-asyncio>=0.21.0; extra == 'dev'
Requires-Dist: pytest-cov>=4.0.0; extra == 'dev'
Requires-Dist: pytest>=7.0.0; extra == 'dev'
Requires-Dist: ruff>=0.1.0; extra == 'dev'
Provides-Extra: pgvector
Requires-Dist: pgvector>=0.2.4; extra == 'pgvector'
Provides-Extra: pinecone
Requires-Dist: pinecone>=7.3.0; extra == 'pinecone'
Provides-Extra: postgresql
Requires-Dist: psycopg[async,binary]>=3.2.9; extra == 'postgresql'
Provides-Extra: qdrant
Requires-Dist: qdrant-client>=1.15.1; extra == 'qdrant'
